pdfitdown/__init__.py
pdfitdown/cli/__init__.py
pdfitdown/cli/app.py
pdfitdown/pdfconversion/__init__.py
pdfitdown/pdfconversion/_default_callback.py
pdfitdown/pdfconversion/converter.py
pdfitdown/pdfconversion/errors.py
pdfitdown/pdfconversion/models.py
pdfitdown/server/__init__.py
pdfitdown/server/serve.py
pdfitdown-2.0.3.dist-info/WHEEL
pdfitdown-2.0.3.dist-info/entry_points.txt
pdfitdown-2.0.3.dist-info/METADATA
pdfitdown-2.0.3.dist-info/RECORD
