Metadata-Version: 2.3
Name: pdfitdown
Version: 2.0.3
Summary: PdfItDown - Convert Everything to PDF
Author: Clelia Astra Bertelli
Author-email: Clelia Astra Bertelli <astraberte9@gmail.com>
Classifier: Programming Language :: Python :: 3
Classifier: License :: OSI Approved :: MIT License
Classifier: Operating System :: OS Independent
Requires-Dist: markdown-pdf>=1.7,<1.8
Requires-Dist: img2pdf>=0.6.3,<1
Requires-Dist: pillow>=11.2.1,<12
Requires-Dist: markitdown[docx,pdf,pptx,xls,xlsx]>=0.1.4,<0.2
Requires-Dist: typer>=0.20.0
Requires-Dist: httpx>=0.28.1,<1 ; extra == 'server'
Requires-Dist: python-multipart>=0.0.20 ; extra == 'server'
Requires-Dist: starlette>=0.46.2 ; extra == 'server'
Requires-Python: >=3.10, <3.14
Project-URL: Homepage, https://github.com/AstraBert/PdfItDown
Project-URL: Issues, https://github.com/AstraBert/PdfItDown/issues
Provides-Extra: server
